circuitmatter/__init__.py
circuitmatter/case.py
circuitmatter/certificates.py
circuitmatter/crypto.py
circuitmatter/data_model.py
circuitmatter/exchange.py
circuitmatter/interaction_model.py
circuitmatter/message.py
circuitmatter/nonvolatile.py
circuitmatter/pase.py
circuitmatter/protocol.py
circuitmatter/session.py
circuitmatter/subscription.py
circuitmatter/tlv.py
circuitmatter/clusters/__init__.py
circuitmatter/clusters/device_management/__init__.py
circuitmatter/clusters/device_management/basic_information.py
circuitmatter/clusters/device_management/general_commissioning.py
circuitmatter/clusters/device_management/general_diagnostics.py
circuitmatter/clusters/device_management/group_key_management.py
circuitmatter/clusters/device_management/network_commissioning.py
circuitmatter/clusters/device_management/node_operational_credentials.py
circuitmatter/clusters/general/__init__.py
circuitmatter/clusters/general/identify.py
circuitmatter/clusters/general/level_control.py
circuitmatter/clusters/general/on_off.py
circuitmatter/clusters/lighting/__init__.py
circuitmatter/clusters/lighting/color_control.py
circuitmatter/clusters/system_model/__init__.py
circuitmatter/clusters/system_model/access_control.py
circuitmatter/clusters/system_model/binding.py
circuitmatter/clusters/system_model/descriptor.py
circuitmatter/clusters/system_model/user_label.py
circuitmatter/device_types/__init__.py
circuitmatter/device_types/simple_device.py
circuitmatter/device_types/lighting/__init__.py
circuitmatter/device_types/lighting/color_temperature.py
circuitmatter/device_types/lighting/dimmable.py
circuitmatter/device_types/lighting/extended_color.py
circuitmatter/device_types/lighting/on_off.py
circuitmatter/device_types/utility/__init__.py
circuitmatter/device_types/utility/root_node.py
circuitmatter/utility/__init__.py
circuitmatter/utility/random.py
circuitmatter/utility/recording.py
circuitmatter/utility/replay.py
circuitmatter/utility/mdns/__init__.py
circuitmatter-0.4.1.dist-info/LICENSE
circuitmatter-0.4.1.dist-info/METADATA
circuitmatter-0.4.1.dist-info/WHEEL
circuitmatter-0.4.1.dist-info/top_level.txt
circuitmatter-0.4.1.dist-info/RECORD
