Metadata-Version: 2.1
Name: circuitmatter
Version: 0.4.1
Author-email: Scott Shawcroft <scott@adafruit.com>
License: The MIT License (MIT)
Project-URL: Home, https://github.com/adafruit/circuitmatter
Project-URL: Bug Tracker, https://github.com/adafruit/circuitmatter/issues
Classifier: License :: OSI Approved :: MIT License
Requires-Python: >=3.11
License-File: LICENSE
Requires-Dist: cryptography
Requires-Dist: ecdsa
Requires-Dist: qrcode
Requires-Dist: Adafruit-Blinka
Provides-Extra: optional
Requires-Dist: hypothesis; extra == "optional"
Requires-Dist: pytest; extra == "optional"
Requires-Dist: pytest-cov; extra == "optional"
Requires-Dist: typing-extensions; extra == "optional"
